README
setup.py
virtualenvwrapper/__init__.py
virtualenvwrapper/django_project.py
virtualenvwrapper.django_template.egg-info/PKG-INFO
virtualenvwrapper.django_template.egg-info/SOURCES.txt
virtualenvwrapper.django_template.egg-info/dependency_links.txt
virtualenvwrapper.django_template.egg-info/entry_points.txt
virtualenvwrapper.django_template.egg-info/namespace_packages.txt
virtualenvwrapper.django_template.egg-info/not-zip-safe
virtualenvwrapper.django_template.egg-info/top_level.txt
virtualenvwrapper/django_project_template/README.md
virtualenvwrapper/django_project_template/manage.py
virtualenvwrapper/django_project_template/requirements.txt
virtualenvwrapper/django_project_template/app/__init__.py
virtualenvwrapper/django_project_template/app/settings.py
virtualenvwrapper/django_project_template/app/urls.py
virtualenvwrapper/django_project_template/app/views.py
virtualenvwrapper/django_project_template/app/wsgi.py
virtualenvwrapper/django_project_template/app/templates/404.html
virtualenvwrapper/django_project_template/app/templates/500.html
virtualenvwrapper/django_project_template/app/templates/base.html
virtualenvwrapper/django_project_template/app/templates/index.html
virtualenvwrapper/django_project_template/app/templates/robots.txt
virtualenvwrapper/django_project_template/app/templates/mail/base.html
virtualenvwrapper/django_project_template/media/.gitkeep
virtualenvwrapper/django_project_template/redirects/.gitkeep
virtualenvwrapper/django_project_template/static/.gitkeep