Metadata-Version: 1.1
Name: virtualenvwrapper.django-template
Version: 0.2
Summary: virtualenvwrapper plugin to create a template Django application
Home-page: http://chrispro.to/projects/virtualenvwrapper-django-template
Author: Chris Proto
Author-email: chroto24@gmail.com
License: UNKNOWN
Platform: Any
Classifier: Development Status :: 3 - Alpha
Classifier: License :: OSI Approved :: BSD License
Classifier: Programming Language :: Python
Classifier: Programming Language :: Python :: 2
Classifier: Intended Audience :: Developers
Classifier: Environment :: Console
Classifier: Framework :: Django
Requires: virtualenv
Requires: virtualenvwrapper (>=2.9)
Provides: virtualenvwrapper.django
